Metadata-Version: 2.1
Name: listr
Version: 1.0.1
Summary: python list with pointer
Home-page: https://fb.me/Slamet. HidayatCirebon
Author: Slamet Hidayat
Author-email: myawn@pm.me
License: MIT
Keywords: list pointer
Platform: UNKNOWN
